{
  "name": "Monarch Synth",
  "description": "Transforms a guitar signal into a powerful monophonic synth sound by using pitch detection to drive a sawtooth oscillator with filter, distortion, and mix controls.",
  "audio": "audio/monarch_synth.sc",
  "visual": "visual/oscilloscope.js",
  "params": [
    {
      "name": "synthOctave",
      "value": 0,
      "range": [-2, 2]
    },
    {
      "name": "synthFilterCutoff",
      "value": 100,
      "range": [20, 2000]
    },
    {
      "name": "synthFilterResonance",
      "value": 0.2,
      "range": [0, 1]
    },
    {
      "name": "synthDrive",
      "value": 0.1,
      "range": [0, 1]
    },
    {
      "name": "mix",
      "value": 0.5,
      "range": [0, 1]
    }
  ]
}